MANIFEST.in
README.rst
setup.py
htmlize/__init__.py
htmlize/command.py
htmlize/compat.py
htmlize.egg-info/PKG-INFO
htmlize.egg-info/SOURCES.txt
htmlize.egg-info/dependency_links.txt
htmlize.egg-info/entry_points.txt
htmlize.egg-info/not-zip-safe
htmlize.egg-info/requires.txt
htmlize.egg-info/top_level.txt
htmlize/resources/avenir-white.css
htmlize/resources/default.css
htmlize/resources/foghorn.css
htmlize/resources/screen.css
htmlize/resources/swiss.css
htmlize/tests/__init__.py
htmlize/tests/test_detect.py