Metadata-Version: 1.1
Name: htmlize
Version: 0.2.2
Summary: tiny utility command, generate html from any formats(e.g. .md, .rst)
Home-page: UNKNOWN
Author: UNKNOWN
Author-email: UNKNOWN
License: UNKNOWN
Platform: UNKNOWN
Classifier: Programming Language :: Python
Classifier: Programming Language :: Python :: Implementation :: CPython
